wiktionary/__init__.py
wiktionary/py.typed
wiktionary_org-1.0.1.dist-info/LICENSE
wiktionary_org-1.0.1.dist-info/METADATA
wiktionary_org-1.0.1.dist-info/WHEEL
wiktionary_org-1.0.1.dist-info/entry_points.txt
wiktionary_org-1.0.1.dist-info/RECORD
