Metadata-Version: 2.3
Name: wiktionary-org
Version: 1.0.1
Summary: Wiktionary on-demand scrapper.
License: BSD-2-Clause
Author: Josiah Kaviani
Author-email: proofit404@gmail.com
Classifier: License :: OSI Approved :: BSD License
Classifier: Programming Language :: Python :: 2
Classifier: Programming Language :: Python :: 2.7
Classifier: Programming Language :: Python :: 3
Classifier: Programming Language :: Python :: 3.4
Classifier: Programming Language :: Python :: 3.5
Classifier: Programming Language :: Python :: 3.6
Classifier: Programming Language :: Python :: 3.7
Classifier: Programming Language :: Python :: 3.8
Classifier: Programming Language :: Python :: 3.9
Classifier: Programming Language :: Python :: 3.10
Classifier: Programming Language :: Python :: 3.11
Classifier: Programming Language :: Python :: 3.12
Classifier: Programming Language :: Python :: 3.13
Requires-Dist: beautifulsoup4
Requires-Dist: click
Requires-Dist: httpx
Project-URL: Changelog, https://proofit404.github.io/wiktionary/changelog
Project-URL: Documentation, https://proofit404.github.io/wiktionary
Project-URL: Homepage, https://pypi.org/project/wiktionary
Project-URL: Issues, https://github.com/proofit404/wiktionary/issues
Project-URL: Repository, https://github.com/proofit404/wiktionary
Project-URL: Twitter, https://twitter.com/proofit404
